ibgeparser/__init__.py
ibgeparser/enums.py
ibgeparser/log.py
ibgeparser/microdados.py
ibge_parser-1.0.2.dist-info/LICENSE
ibge_parser-1.0.2.dist-info/METADATA
ibge_parser-1.0.2.dist-info/WHEEL
ibge_parser-1.0.2.dist-info/top_level.txt
ibge_parser-1.0.2.dist-info/RECORD
