Metadata-Version: 2.1
Name: ibge-parser
Version: 1.0.2
Summary: IBGE Parser is a Python library to get microdata from IBGE - (Instituto Brasileiro de Geografia e Estatística) census and convert the data to readable CSV files.
Home-page: https://github.com/SeniorSA/ibge-parser
Author: Senior Sistemas - Senior Labs
Author-email: research@senior.com.br
License: UNKNOWN
Platform: UNKNOWN
Classifier: Programming Language :: Python :: 3
Classifier: License :: OSI Approved :: Apache Software License
Classifier: Operating System :: OS Independent
Requires-Python: >=3.6
Requires-Dist: logzero (==1.5.0)
